phenomorph/__init__.py
phenomorph/_version.py
phenomorph/model.py
phenomorph/utils.py
phenomorph-1.0.3.dist-info/LICENSE
phenomorph-1.0.3.dist-info/METADATA
phenomorph-1.0.3.dist-info/WHEEL
phenomorph-1.0.3.dist-info/top_level.txt
phenomorph-1.0.3.dist-info/RECORD
