Metadata-Version: 2.1
Name: phenomorph
Version: 1.0.3
Summary: A mlmorph module for phenopype
Home-page: https://www.phenopype.org
Author: Arthur Porto
Author-email: agporto@gmail.com
License: LGPL
Platform: UNKNOWN
License-File: LICENSE
Requires-Dist: phenopype
Requires-Dist: dlib
